tcsamcli/__init__.py
tcsamcli/__main__.py
tcsamcli/template_builder.py
tc_sam_cli-0.0.12.dist-info/entry_points.txt
tc_sam_cli-0.0.12.dist-info/LICENSE
tc_sam_cli-0.0.12.dist-info/WHEEL
tc_sam_cli-0.0.12.dist-info/METADATA
tc_sam_cli-0.0.12.dist-info/RECORD
