Metadata-Version: 2.1
Name: tc-sam-cli
Version: 0.0.12
Summary: Tc sam cli
Home-page: https://github.com/trustcruit/tc-sam-cli/
License: UNKNOWN
Author: Niels Lemmens
Author-email: draso.odin@gmail.com
Requires-Python: >=3.7
Classifier: Development Status :: 2 - Pre-Alpha
Classifier: License :: OSI Approved :: MIT License
Classifier: Programming Language :: Python :: 3.7
Classifier: Topic :: Software Development :: Build Tools
Requires-Dist: aws-sam-cli==0.37.0
Requires-Dist: click
Requires-Dist: sh
Requires-Dist: toml
Requires-Dist: tclambda
